pynecil/__init__.py
pynecil/client.py
pynecil/const.py
pynecil/exceptions.py
pynecil/py.typed
pynecil/types.py
pynecil/update.py
pynecil-4.2.1.dist-info/METADATA
pynecil-4.2.1.dist-info/WHEEL
pynecil-4.2.1.dist-info/licenses/LICENSE
pynecil-4.2.1.dist-info/RECORD
