Metadata-Version: 2.4
Name: pynecil
Version: 4.2.1
Summary: Python library to communicate with Pinecil V2 soldering irons via Bluetooth
Project-URL: Documentation, https://tr4nt0r.github.io/pynecil/
Project-URL: Source, https://github.com/tr4nt0r/pynecil
Author-email: Manfred Dennerlein Rodelo <manfred@dennerlein.name>
License-Expression: MIT
License-File: LICENSE
Classifier: Operating System :: OS Independent
Classifier: Programming Language :: Python :: 3 :: Only
Requires-Python: >=3.11
Requires-Dist: aiohttp>=3.11.10
Requires-Dist: bleak-retry-connector>=4.3.0
Requires-Dist: bleak>=0.22.0
Requires-Dist: bluetooth-adapters>=2.1.0; python_version >= '3.14'
